bobochic_api_client/__init__.py
bobochic_api_client/client.py
bobochic_api_client/utils.py
bobochic_api_client-0.0.7.dist-info/LICENSE
bobochic_api_client-0.0.7.dist-info/METADATA
bobochic_api_client-0.0.7.dist-info/WHEEL
bobochic_api_client-0.0.7.dist-info/top_level.txt
bobochic_api_client-0.0.7.dist-info/RECORD
